{
  "indexes": [
    {
      "collectionGroup": "products",
      "queryScope": "COLLECTION",
      "fields": [
        {
          "fieldPath": "isActive",
          "order": "ASCENDING"
        },
        {
          "fieldPath": "categoryId",
          "order": "ASCENDING"
        }
      ]
    },
    {
      "collectionGroup": "products",
      "queryScope": "COLLECTION",
      "fields": [
        {
          "fieldPath": "isActive",
          "order": "ASCENDING"
        },
        {
          "fieldPath": "brand",
          "order": "ASCENDING"
        }
      ]
    },
    {
      "collectionGroup": "products",
      "queryScope": "COLLECTION",
      "fields": [
        {
          "fieldPath": "stock",
          "order": "ASCENDING"
        },
        {
          "fieldPath": "minStock",
          "order": "ASCENDING"
        }
      ]
    },
    {
      "collectionGroup": "products",
      "queryScope": "COLLECTION",
      "fields": [
        {
          "fieldPath": "compatibility",
          "arrayConfig": "CONTAINS"
        },
        {
          "fieldPath": "isActive",
          "order": "ASCENDING"
        }
      ]
    },
    {
      "collectionGroup": "products",
      "queryScope": "COLLECTION",
      "fields": [
        {
          "fieldPath": "sku",
          "order": "ASCENDING"
        },
        {
          "fieldPath": "isActive",
          "order": "ASCENDING"
        }
      ]
    },
    {
      "collectionGroup": "workOrders",
      "queryScope": "COLLECTION",
      "fields": [
        {
          "fieldPath": "status",
          "order": "ASCENDING"
        },
        {
          "fieldPath": "createdAt",
          "order": "ASCENDING"
        }
      ]
    },
    {
      "collectionGroup": "users",
      "queryScope": "COLLECTION",
      "fields": [
        {
          "fieldPath": "role",
          "order": "ASCENDING"
        },
        {
          "fieldPath": "active",
          "order": "ASCENDING"
        }
      ]
    },
    {
      "collectionGroup": "appointments",
      "queryScope": "COLLECTION",
      "fields": [
        {
          "fieldPath": "scheduledAt",
          "order": "ASCENDING"
        },
        {
          "fieldPath": "status",
          "order": "ASCENDING"
        }
      ]
    },
    {
      "collectionGroup": "auditLog",
      "queryScope": "COLLECTION",
      "fields": [
        {
          "fieldPath": "performedAt",
          "order": "ASCENDING"
        },
        {
          "fieldPath": "action",
          "order": "ASCENDING"
        }
      ]
    },
    {
      "collectionGroup": "workOrders",
      "queryScope": "COLLECTION",
      "fields": [
        {
          "fieldPath": "assignedTo",
          "order": "ASCENDING"
        },
        {
          "fieldPath": "status",
          "order": "ASCENDING"
        }
      ]
    },
    {
      "collectionGroup": "workOrders",
      "queryScope": "COLLECTION",
      "fields": [
        {
          "fieldPath": "assignedTo",
          "order": "ASCENDING"
        },
        {
          "fieldPath": "status",
          "order": "ASCENDING"
        },
        {
          "fieldPath": "createdAt",
          "order": "ASCENDING"
        }
      ]
    },
    {
      "collectionGroup": "technicianMetrics",
      "queryScope": "COLLECTION",
      "fields": [
        {
          "fieldPath": "technicianId",
          "order": "ASCENDING"
        },
        {
          "fieldPath": "periodEnd",
          "order": "DESCENDING"
        }
      ]
    },
    {
      "collectionGroup": "userVehicles",
      "queryScope": "COLLECTION",
      "fields": [
        {
          "fieldPath": "userId",
          "order": "ASCENDING"
        },
        {
          "fieldPath": "baseVehicleId",
          "order": "ASCENDING"
        }
      ]
    },
    {
      "collectionGroup": "motorcycleAssignments",
      "queryScope": "COLLECTION",
      "fields": [
        {
          "fieldPath": "userId",
          "order": "ASCENDING"
        },
        {
          "fieldPath": "motorcycleId",
          "order": "ASCENDING"
        },
        {
          "fieldPath": "status",
          "order": "ASCENDING"
        }
      ]
    },
    {
      "collectionGroup": "timeEntries",
      "queryScope": "COLLECTION",
      "fields": [
        {
          "fieldPath": "technicianId",
          "order": "ASCENDING"
        },
        {
          "fieldPath": "endAt",
          "order": "ASCENDING"
        },
        {
          "fieldPath": "startAt",
          "order": "DESCENDING"
        }
      ]
    }
  ],
  "fieldOverrides": []
}